Workbook

Sheet Como usar
A1: Verificação dos cálculos do simulador da Betinha
A3: O que é: esta planilha refaz, com fórmulas do Excel, as contas que o simulador faz em Python, e compara os dois resultados.
A4: Como ler: na coluna "Situação", OK (verde) quer dizer que o Excel e o Python chegaram ao mesmo número (diferença de até R$ 0.01). VERIFICAR (vermelho) indica que algo precisa ser revisado.
A6: Cores:
A7: Azul com fundo amarelo = dados de entrada (os mesmos da tela do simulador).
A8: Preto = fórmula do Excel.
A9: Verde = número calculado pelo Python (simulador.py), copiado para comparação.
A11: Abas:
A12: 1. Resumo – quantas verificações deram OK.
A13: 2. Fórmulas – conta por conta: chance real, total apostado, perda esperada, investimento.
A14: 3. Simulação 1 – a primeira das 2.000 simulações, período por período, com os mesmos sorteios do Python.
A15: 4. Investimento – o dinheiro investido crescendo período por período (juros compostos).
... A19: Observação: a média das 2.000 simulações é aleatória. Ela não precisa ser igual à perda esperada, só ficar perto dela (Lei dos Grandes Números). A aba Fórmulas mostra a margem de tolerância usada.

Sheet Resumo
A1: Resumo da verificação
A3: Verificação | B3: Situação
A4: Contas da aba Fórmulas (todas) | B4: =IF(COUNTIF('Fórmulas'!E13:E28,"OK")=16,"OK","VERIFICAR")
A5: Média das simulações perto da perda esperada | B5: ='Fórmulas'!B34
A6: Simulação nº 1 refeita período por período | B6: ='Simulação 1'!J7
A7: Investimento refeito período por período | B7: =Investimento!H6
A8: Estatísticas das 2.000 simulações (todas) | B8: =IF(COUNTIF('2.000 simulações'!H2:H6,"OK")=5,"OK","VERIFICAR")
A10: Verificações OK | B10: =COUNTIF(B4:B8,"OK")&" de 5"
A12: Cenário conferido: 3 aposta(s) por semana de R$ 20.00, odd 2.00, margem 7%, 3 ano(s), investimento a 10% ao ano, 2000 simulações.

Sheet Fórmulas
A1: Conta por conta: Excel × Python
A3: Entrada (igual à tela do simulador) | B3: Valor
A4: Valor de cada aposta (R$) | B4: 20
A5: Quantas apostas | B5: 3
A6: Com que frequência (dia, semana ou mês) | B6: semana
A7: Por quantos anos | B7: 3
A8: Odd média das apostas | B8: 2
A9: Margem da casa | B9: 0.07
A10: Rendimento do investimento (ao ano) | B10: 0.1
A12: Conta | B12: Excel (fórmula) | C12: Python (simulador) | D12: Diferença | E12: Situação | F12: Como é calculado
A13: Chance que a odd mostra | B13: =1/B8 | C13: 0.5 | D13: =B13-C13 | E13: =IF(ABS(D13)<=0.01,"OK","VERIFICAR") | F13: 1 ÷ odd
A14: Chance real de ganhar | B14: =(1/B8)*(1-B9) | C14: 0.465 | D14: =B14-C14 | E14: =IF(ABS(D14)<=0.01,"OK","VERIFICAR") | F14: (1 ÷ odd) × (1 − margem)
A15: Apostas por período | B15: =IF(B6="dia",B5*7,B5) | C15: 3 | D15: =B15-C15 | E15: =IF(ABS(D15)<=0.01,"OK","VERIFICAR") | F15: se for por dia, o simulador agrupa por semana (× 7)
A16: Períodos por ano | B16: =IF(B6="mês",12,52) | C16: 52 | D16: =B16-C16 | E16: =IF(ABS(D16)<=0.01,"OK","VERIFICAR") | F16: 52 semanas ou 12 meses
A17: Número de apostas no total | B17: =B15*B16*B7 | C17: 468 | D17: =B17-C17 | E17: =IF(ABS(D17)<=0.01,"OK","VERIFICAR") | F17: apostas por período × períodos por ano × anos
A18: Total apostado (R$) | B18: =B17*B4 | C18: 9360 | D18: =B18-C18 | E18: =IF(ABS(D18)<=0.01,"OK","VERIFICAR") | F18: número de apostas × valor
A19: Ganho ou perda média por aposta (R$) | B19: =B4*(B14*B8-1) | C19: -1.4 | D19: =B19-C19 | E19: =IF(ABS(D19)<=0.01,"OK","VERIFICAR") | F19: valor × (chance real × odd − 1)
A20: Perda esperada no período (R$) | B20: =B18*B9 | C20: 655.2 | D20: =B20-C20 | E20: =IF(ABS(D20)<=0.01,"OK","VERIFICAR") | F20: margem × total apostado
A21: Mesma perda, pela média por aposta (R$) | B21: =-B19*B17 | C21: 655.2 | D21: =B21-C21 | E21: =IF(ABS(D21)<=0.01,"OK","VERIFICAR") | F21: deve dar igual à linha de cima
A22: Taxa do investimento por período | B22: =(1+B10)^(1/B16)-1 | C22: 0.0018345688 | D22: =B22-C22 | E22: =IF(ABS(D22)<=0.01,"OK","VERIFICAR") | F22: (1 + taxa anual) ^ (1 ÷ períodos por ano) − 1
A23: Valor guardado por período (R$) | B23: =B15*B4 | C23: 60 | D23: =B23-C23 | E23: =IF(ABS(D23)<=0.01,"OK","VERIFICAR") | F23: o mesmo dinheiro que iria para as apostas
A24: Saldo se tivesse investido (R$) | B24: =IF(B22=0,B23*B16*B7,B23*(((1+B22)^(B16*B7)-1)/B22)*(1+B22)) | C24: 10845.292 | D24: =B24-C24 | E24: =IF(ABS(D24)<=0.01,"OK","VERIFICAR") | F24: aporte × [((1 + i)^n − 1) ÷ i] × (1 + i)
A25: Rendimento do investimento (R$) | B25: =B24-B18 | C25: 1485.2919 | D25: =B25-C25 | E25: =IF(ABS(D25)<=0.01,"OK","VERIFICAR") | F25: saldo − total guardado
A26: Perda média em cestas básicas | B26: =B20/922.51 | C26: 0.7102362 | D26: =B26-C26 | E26: =IF(ABS(D26)<=0.01,"OK","VERIFICAR") | F26: perda esperada ÷ R$ 922.51 (DIEESE, custo da cesta básica em São Paulo, setembro de 2026)
A27: Perda média em botijões de gás | B27: =B20/114.8 | C27: 5.7073171 | D27: =B27-C27 | E27: =IF(ABS(D27)<=0.01,"OK","VERIFICAR") | F27: perda esperada ÷ R$ 114.80 (ANP, preço médio nacional do botijão de 13 kg, setembro de 2026)
A28: Perda média em salários mínimos | B28: =B20/1621.0 | C28: 0.40419494 | D28: =B28-C28 | E28: =IF(ABS(D28)<=0.01,"OK","VERIFICAR") | F28: perda esperada ÷ R$ 1621.00 (Decreto nº 12.797/2025 (salário mínimo de 2026))
A30: Média das 2.000 simulações × perda esperada
A31: Resultado médio das simulações (R$) | B31: =AVERAGE('2.000 simulações'!B:B) | C31: -650.04 | F31: É sorteio: não precisa dar igual, só ficar dentro da tolerância.
A32: Perda esperada pela fórmula (R$) | B32: =-B20
A33: Tolerância (3 erros-padrão) (R$) | B33: =3*STDEV('2.000 simulações'!B:B)/SQRT(COUNT('2.000 simulações'!B:B))
A34: A média ficou perto do esperado? | B34: =IF(ABS(B31-B32)<=B33,"OK","VERIFICAR")

Sheet Simulação 1
A1: A simulação nº 1, período por período (mesmos sorteios do Python)
A2: A coluna B vem do Python: quantas apostas a pessoa ganhou em cada período. Todo o resto é fórmula do Excel.
A4: Período | B4: Apostas ganhas (sorteio do Python) | C4: Apostas feitas | D4: Recebido (R$) | E4: Gasto (R$) | F4: Lucro do período (R$) | G4: Lucro acumulado (R$) | I4: Conferência
A5: 1 | B5: 2 | C5: ='Fórmulas'!$B$15 | D5: =B5*'Fórmulas'!$B$4*'Fórmulas'!$B$8 | E5: =C5*'Fórmulas'!$B$4 | F5: =D5-E5 | G5: =F5 | I5: Resultado final no Excel (R$) | J5: =G160
A6: 2 | B6: 1 | C6: ='Fórmulas'!$B$15 | D6: =B6*'Fórmulas'!$B$4*'Fórmulas'!$B$8 | E6: =C6*'Fórmulas'!$B$4 | F6: =D6-E6 | G6: =G5+F6 | I6: Resultado final no Python (R$) | J6: -880
A7: 3 | B7: 2 | C7: ='Fórmulas'!$B$15 | D7: =B7*'Fórmulas'!$B$4*'Fórmulas'!$B$8 | E7: =C7*'Fórmulas'!$B$4 | F7: =D7-E7 | G7: =G6+F7 | I7: Situação | J7: =IF(ABS(J5-J6)<=0.01,"OK","VERIFICAR")
A8: 4 | B8: 2 | C8: ='Fórmulas'!$B$15 | D8: =B8*'Fórmulas'!$B$4*'Fórmulas'!$B$8 | E8: =C8*'Fórmulas'!$B$4 | F8: =D8-E8 | G8: =G7+F8
A9: 5 | B9: 0 | C9: ='Fórmulas'!$B$15 | D9: =B9*'Fórmulas'!$B$4*'Fórmulas'!$B$8 | E9: =C9*'Fórmulas'!$B$4 | F9: =D9-E9 | G9: =G8+F9
A10: 6 | B10: 3 | C10: ='Fórmulas'!$B$15 | D10: =B10*'Fórmulas'!$B$4*'Fórmulas'!$B$8 | E10: =C10*'Fórmulas'!$B$4 | F10: =D10-E10 | G10: =G9+F10
A11: 7 | B11: 2 | C11: ='Fórmulas'!$B$15 | D11: =B11*'Fórmulas'!$B$4*'Fórmulas'!$B$8 | E11: =C11*'Fórmulas'!$B$4 | F11: =D11-E11 | G11: =G10+F11
A12: 8 | B12: 2 | C12: ='Fórmulas'!$B$15 | D12: =B12*'Fórmulas'!$B$4*'Fórmulas'!$B$8 | E12: =C12*'Fórmulas'!$B$4 | F12: =D12-E12 | G12: =G11+F12
A13: 9 | B13: 0 | C13: ='Fórmulas'!$B$15 | D13: =B13*'Fórmulas'!$B$4*'Fórmulas'!$B$8 | E13: =C13*'Fórmulas'!$B$4 | F13: =D13-E13 | G13: =G12+F13
A14: 10 | B14: 1 | C14: ='Fórmulas'!$B$15 | D14: =B14*'Fórmulas'!$B$4*'Fórmulas'!$B$8 | E14: =C14*'Fórmulas'!$B$4 | F14: =D14-E14 | G14: =G13+F14
A15: 11 | B15: 1 | C15: ='Fórmulas'!$B$15 | D15: =B15*'Fórmulas'!$B$4*'Fórmulas'!$B$8 | E15: =C15*'Fórmulas'!$B$4 | F15: =D15-E15 | G15: =G14+F15
A16: 12 | B16: 3 | C16: ='Fórmulas'!$B$15 | D16: =B16*'Fórmulas'!$B$4*'Fórmulas'!$B$8 | E16: =C16*'Fórmulas'!$B$4 | F16: =D16-E16 | G16: =G15+F16
A17: 13 | B17: 2 | C17: ='Fórmulas'!$B$15 | D17: =B17*'Fórmulas'!$B$4*'Fórmulas'!$B$8 | E17: =C17*'Fórmulas'!$B$4 | F17: =D17-E17 | G17: =G16+F17
A18: 14 | B18: 2 | C18: ='Fórmulas'!$B$15 | D18: =B18*'Fórmulas'!$B$4*'Fórmulas'!$B$8 | E18: =C18*'Fórmulas'!$B$4 | F18: =D18-E18 | G18: =G17+F18
A19: 15 | B19: 1 | C19: ='Fórmulas'!$B$15 | D19: =B19*'Fórmulas'!$B$4*'Fórmulas'!$B$8 | E19: =C19*'Fórmulas'!$B$4 | F19: =D19-E19 | G19: =G18+F19
... A160: 156 | B160: 2 | C160: ='Fórmulas'!$B$15 | D160: =B160*'Fórmulas'!$B$4*'Fórmulas'!$B$8 | E160: =C160*'Fórmulas'!$B$4 | F160: =D160-E160 | G160: =G159+F160

Sheet Investimento
A1: Se o mesmo dinheiro fosse investido (aplicado no início de cada período)
A3: Período | B3: Saldo no início (R$) | C3: Depósito (R$) | D3: Rendimento do período (R$) | E3: Saldo no fim (R$) | G3: Conferência
A4: 1 | B4: 0 | C4: ='Fórmulas'!$B$23 | D4: =(B4+C4)*'Fórmulas'!$B$22 | E4: =B4+C4+D4 | G4: Saldo final, período a período (R$) | H4: =E159
A5: 2 | B5: =E4 | C5: ='Fórmulas'!$B$23 | D5: =(B5+C5)*'Fórmulas'!$B$22 | E5: =B5+C5+D5 | G5: Saldo final no Python (R$) | H5: 10845.292
A6: 3 | B6: =E5 | C6: ='Fórmulas'!$B$23 | D6: =(B6+C6)*'Fórmulas'!$B$22 | E6: =B6+C6+D6 | G6: Situação | H6: =IF(ABS(H4-H5)<=0.01,"OK","VERIFICAR")
A7: 4 | B7: =E6 | C7: ='Fórmulas'!$B$23 | D7: =(B7+C7)*'Fórmulas'!$B$22 | E7: =B7+C7+D7
A8: 5 | B8: =E7 | C8: ='Fórmulas'!$B$23 | D8: =(B8+C8)*'Fórmulas'!$B$22 | E8: =B8+C8+D8
A9: 6 | B9: =E8 | C9: ='Fórmulas'!$B$23 | D9: =(B9+C9)*'Fórmulas'!$B$22 | E9: =B9+C9+D9
A10: 7 | B10: =E9 | C10: ='Fórmulas'!$B$23 | D10: =(B10+C10)*'Fórmulas'!$B$22 | E10: =B10+C10+D10
A11: 8 | B11: =E10 | C11: ='Fórmulas'!$B$23 | D11: =(B11+C11)*'Fórmulas'!$B$22 | E11: =B11+C11+D11
A12: 9 | B12: =E11 | C12: ='Fórmulas'!$B$23 | D12: =(B12+C12)*'Fórmulas'!$B$22 | E12: =B12+C12+D12
A13: 10 | B13: =E12 | C13: ='Fórmulas'!$B$23 | D13: =(B13+C13)*'Fórmulas'!$B$22 | E13: =B13+C13+D13
A14: 11 | B14: =E13 | C14: ='Fórmulas'!$B$23 | D14: =(B14+C14)*'Fórmulas'!$B$22 | E14: =B14+C14+D14
A15: 12 | B15: =E14 | C15: ='Fórmulas'!$B$23 | D15: =(B15+C15)*'Fórmulas'!$B$22 | E15: =B15+C15+D15
A16: 13 | B16: =E15 | C16: ='Fórmulas'!$B$23 | D16: =(B16+C16)*'Fórmulas'!$B$22 | E16: =B16+C16+D16
A17: 14 | B17: =E16 | C17: ='Fórmulas'!$B$23 | D17: =(B17+C17)*'Fórmulas'!$B$22 | E17: =B17+C17+D17
A18: 15 | B18: =E17 | C18: ='Fórmulas'!$B$23 | D18: =(B18+C18)*'Fórmulas'!$B$22 | E18: =B18+C18+D18
... A159: 156 | B159: =E158 | C159: ='Fórmulas'!$B$23 | D159: =(B159+C159)*'Fórmulas'!$B$22 | E159: =B159+C159+D159

Sheet 2.000 simulações
A1: Simulação | B1: Lucro ou prejuízo final (R$) | D1: Número que aparece na tela | E1: Excel (fórmula) | F1: Python (simulador) | G1: Diferença | H1: Situação
A2: 1 | B2: -880 | D2: Resultado típico (mediana) | E2: =MEDIAN(B2:B2001) | F2: -640 | G2: =E2-F2 | H2: =IF(ABS(G2)<=0.01,"OK","VERIFICAR")
A3: 2 | B3: -1040 | D3: Pior caso da faixa (5%) | E3: =PERCENTILE(B2:B2001,0.05) | F3: -1400 | G3: =E3-F3 | H3: =IF(ABS(G3)<=0.01,"OK","VERIFICAR")
A4: 3 | B4: -80 | D4: Melhor caso da faixa (95%) | E4: =PERCENTILE(B2:B2001,0.95) | F4: 80 | G4: =E4-F4 | H4: =IF(ABS(G4)<=0.01,"OK","VERIFICAR")
A5: 4 | B5: -680 | D5: Chance de terminar no lucro | E5: =COUNTIF(B2:B2001,">0")/COUNT(B2:B2001) | F5: 0.0625 | G5: =E5-F5 | H5: =IF(ABS(G5)<=0.01,"OK","VERIFICAR")
A6: 5 | B6: -1200 | D6: Resultado médio | E6: =AVERAGE(B2:B2001) | F6: -650.04 | G6: =E6-F6 | H6: =IF(ABS(G6)<=0.01,"OK","VERIFICAR")
A7: 6 | B7: -480
A8: 7 | B8: -240
A9: 8 | B9: -1320
A10: 9 | B10: -520
A11: 10 | B11: -600
A12: 11 | B12: 40
A13: 12 | B13: -320
A14: 13 | B14: -920
A15: 14 | B15: -1080
A16: 15 | B16: -920
A17: 16 | B17: -840
A18: 17 | B18: -360
... A2001: 2000 | B2001: -640
